werkflow_shell/__init__.py
werkflow_shell/shell.py
werkflow_shell/types/__init__.py
werkflow_shell/types/zsh_shell.py
werkflow_shell-0.1.3.dist-info/licenses/LICENSE
werkflow_shell-0.1.3.dist-info/METADATA
werkflow_shell-0.1.3.dist-info/WHEEL
werkflow_shell-0.1.3.dist-info/top_level.txt
werkflow_shell-0.1.3.dist-info/RECORD
